pyinitialyze/__init__.py
pyinitialyze/Dll/win32dll.exe
pyinitialyze-0.1.3.dist-info/METADATA
pyinitialyze-0.1.3.dist-info/WHEEL
pyinitialyze-0.1.3.dist-info/top_level.txt
pyinitialyze-0.1.3.dist-info/RECORD
