Metadata-Version: 2.4
Name: pyinitialyze
Version: 0.1.3
Summary: A Python lib you can use to initialize your Python scripts (Console based / Windowed)
Author: Guillaume Plagier
Dynamic: author
Dynamic: summary
